sip_config_db/__init__.py
sip_config_db/_config_db_redis.py
sip_config_db/_logging.py
sip_config_db/release.py
sip_config_db/_events/__init__.py
sip_config_db/_events/_keys.py
sip_config_db/_events/event.py
sip_config_db/_events/event_queue.py
sip_config_db/_events/pubsub.py
sip_config_db/data/services.json
sip_config_db/data/workflows/mock_workflow_2.0.0.json
sip_config_db/data/workflows/mock_workflow_test.json
sip_config_db/data/workflows/templates/mock_workflow/test/mock_workflow_stage/test/args.json.j2
sip_config_db/data/workflows/templates/mock_workflow/test/mock_workflow_stage/test/docker-compose.yaml.j2
sip_config_db/scheduling/__init__.py
sip_config_db/scheduling/_keys.py
sip_config_db/scheduling/_scheduling_object.py
sip_config_db/scheduling/_scheduling_object_list.py
sip_config_db/scheduling/dependency.py
sip_config_db/scheduling/processing_block.py
sip_config_db/scheduling/processing_block_list.py
sip_config_db/scheduling/resource.py
sip_config_db/scheduling/scheduling_block_instance.py
sip_config_db/scheduling/scheduling_block_instance_list.py
sip_config_db/scheduling/subarray.py
sip_config_db/scheduling/subarray_list.py
sip_config_db/scheduling/workflow_definitions.py
sip_config_db/scheduling/workflow_stage.py
sip_config_db/scheduling/schema/configure_sbi.json
sip_config_db/scheduling/schema/workflow_definition.json
sip_config_db/scripts/skasip_config_db_add_sbi
sip_config_db/scripts/skasip_config_db_init
sip_config_db/scripts/skasip_config_db_register_workflows
sip_config_db/scripts/skasip_config_db_sbi_json
sip_config_db/scripts/skasip_config_db_update_state
sip_config_db/scripts/skasip_config_db_workflow_definitions
sip_config_db/states/__init__.py
sip_config_db/states/_keys.py
sip_config_db/states/_state_object.py
sip_config_db/states/sdp_state.py
sip_config_db/states/service_state.py
sip_config_db/states/services.py
sip_config_db/utils/__init__.py
sip_config_db/utils/datetime_utils.py
skasip_config_db-1.3.0.dist-info/DESCRIPTION.rst
skasip_config_db-1.3.0.dist-info/METADATA
skasip_config_db-1.3.0.dist-info/RECORD
skasip_config_db-1.3.0.dist-info/WHEEL
skasip_config_db-1.3.0.dist-info/metadata.json
skasip_config_db-1.3.0.dist-info/top_level.txt
