Metadata-Version: 2.0
Name: skasip-config-db
Version: 1.3.0
Summary: SIP Execution Control Configuration Database library.
Home-page: https://github.com/SKA-ScienceDataProcessor/integration-prototype/tree/master/sip/execution_control/configuration_db
Author: SKA SDP SIP team.
License: UNKNOWN
Platform: UNKNOWN
Classifier: Programming Language :: Python :: 3 :: Only
Classifier: Development Status :: 1 - Planning
Classifier: License :: OSI Approved :: BSD License
Requires-Dist: redis (==2.10.6)
Requires-Dist: jsonschema (==2.6.0)
Requires-Dist: jinja2 (==2.10)
Requires-Dist: PyYAML (==4.2b4)
